arboristo/__init__.py
arboristo/arbor.py
arboristo-0.1.1.dist-info/LICENSE
arboristo-0.1.1.dist-info/WHEEL
arboristo-0.1.1.dist-info/METADATA
arboristo-0.1.1.dist-info/RECORD
