Metadata-Version: 2.1
Name: arboristo
Version: 0.1.1
Summary: A light-weight package to lazily traverse a deeply nested dictionary
Home-page: https://github.com/AlanAutomated/arboristo
License: MIT
Keywords: dictionary,deep,lazy,nested
Author: Alan Haynes
Author-email: alan@nre.dev
Requires-Python: >=3.8,<4.0
Classifier: License :: OSI Approved :: MIT License
Classifier: Programming Language :: Python :: 3
Classifier: Programming Language :: Python :: 3.8
Classifier: Programming Language :: Python :: 3.9
Classifier: Topic :: Software Development :: Libraries
Classifier: Topic :: Software Development :: Libraries :: Python Modules
Project-URL: Documentation, https://github.com/AlanAutomated/arboristo
Project-URL: Repository, https://github.com/AlanAutomated/arboristo
